{
	"configurations" : 
	[
		{
			"directories" : 
			[
				{
					"build" : ".",
					"jsonFile" : "directory-.-Debug-f5ebdc15457944623624.json",
					"minimumCMakeVersion" : 
					{
						"string" : "3.26"
					},
					"projectIndex" : 0,
					"source" : ".",
					"targetIndexes" : 
					[
						0
					]
				}
			],
			"name" : "Debug",
			"projects" : 
			[
				{
					"directoryIndexes" : 
					[
						0
					],
					"name" : "GraphProject",
					"targetIndexes" : 
					[
						0
					]
				}
			],
			"targets" : 
			[
				{
					"directoryIndex" : 0,
					"id" : "GraphProject::@6890427a1f51a3e7e1df",
					"jsonFile" : "target-GraphProject-Debug-a9f47770616d19eac6b0.json",
					"name" : "GraphProject",
					"projectIndex" : 0
				}
			]
		}
	],
	"kind" : "codemodel",
	"paths" : 
	{
		"build" : "/home/davidm-g/Documents/DA/project_DA/cmake-build-debug",
		"source" : "/home/davidm-g/Documents/DA/project_DA"
	},
	"version" : 
	{
		"major" : 2,
		"minor" : 6
	}
}
